[
    {
        "STT":"No.",
        "Tên Hàng Hóa, Dịch Vụ":"Description",
        "Số Lượng - Đơn Vị Tính":"Quantity - Unit",
        "Đơn Giá":"Unit Price",
        "Tiền Trước Thuế(VNĐ)":"Exclude VAT",
        "Tiền Thuế":"%",
        "Tiền Thuế_VAT":"VAT Amount",
        "Thành Tiền":"Total Amount"
    },
    {
        "STT":"1",
        "Tên Hàng Hóa, Dịch Vụ":"2",
        "Số Lượng - Đơn Vị Tính":"3",
        "Đơn Giá":"4",
        "Tiền Trước Thuế(VNĐ)":"5 = 3 x 4",
        "Tiền Thuế":"6",
        "Tiền Thuế_VAT":"7",
        "Thành Tiền":"8"
    },
    {
        "STT":"1",
        "Tên Hàng Hóa, Dịch Vụ":"THU HỘ CHỦ TÀU PHÍ BẢO TRÌ THIẾT BỊ ( EMCI ) E254JOCS 144FX17993 04\/01\/2026 S\/N:",
        "Số Lượng - Đơn Vị Tính":"1 20\" CONT",
        "Đơn Giá":"300.000",
        "Tiền Trước Thuế(VNĐ)":"300.000",
        "Tiền Thuế":"KHAC",
        "Tiền Thuế_VAT":"15.789",
        "Thành Tiền":"315.789"
    },
    {
        "STT":"2",
        "Tên Hàng Hóa, Dịch Vụ":"THU HỘ PHÍ VỆ SINH CONTS ( CLCO ). E254JOCS 144FX17993 04\/01\/2026 S\/N:",
        "Số Lượng - Đơn Vị Tính":"1 20\" CONT",
        "Đơn Giá":"250.000",
        "Tiền Trước Thuế(VNĐ)":"250.000",
        "Tiền Thuế":"KHAC",
        "Tiền Thuế_VAT":"13.158",
        "Thành Tiền":"263.158"
    },
    {
        "STT":"3",
        "Tên Hàng Hóa, Dịch Vụ":"THU HỘ PHÍ CHỨNGTỪ ( DOC FEE) E254JOCS 144FX17993 04\/01\/2026 S\/N:",
        "Số Lượng - Đơn Vị Tính":"1 BỘ",
        "Đơn Giá":"1.100.000",
        "Tiền Trước Thuế(VNĐ)":"1.100.000",
        "Tiền Thuế":"KHAC",
        "Tiền Thuế_VAT":"57.895",
        "Thành Tiền":"1.157.895"
    },
    {
        "STT":"4",
        "Tên Hàng Hóa, Dịch Vụ":"THU HỘ PHÍ LÀMHÀNG TẠI CẢNG( THC ) E254JOCS 144FX17993 04\/01\/2026 S\/N:",
        "Số Lượng - Đơn Vị Tính":"1 20\" CONT",
        "Đơn Giá":"3.400.000",
        "Tiền Trước Thuế(VNĐ)":"3.400.000",
        "Tiền Thuế":"KHAC",
        "Tiền Thuế_VAT":"178.947",
        "Thành Tiền":"3.578.947"
    },
    {
        "STT":"Tổng Cộng VND (Grand Total VND) :",
        "Tên Hàng Hóa, Dịch Vụ":"Tổng Cộng VND (Grand Total VND) :",
        "Số Lượng - Đơn Vị Tính":"Tổng Cộng VND (Grand Total VND) :",
        "Đơn Giá":"Tổng Cộng VND (Grand Total VND) :",
        "Tiền Trước Thuế(VNĐ)":"5.050.000",
        "Tiền Thuế":"",
        "Tiền Thuế_VAT":"265.789",
        "Thành Tiền":"5.315.789"
    }
]